<?xml version="1.0" encoding="UTF-8"?>
<vivadoHLSLog:LogRoot xmlns:vivadoHLSLog="www.xilinx.com/vivadoHLSLog">
  <errorLogs>
    <logs>
      <synLog/>
      <simLog/>
      <mgLog/>
      <packageLog/>
      <csimLog/>
    </logs>
  </errorLogs>
  <warningLogs>
    <logs>
      <synLog>
        <logs message="WARNING: [HLS 200-433] Loop - Loop 1 has an initiation interval that is equal to the pipeline depth (1) - this results in an unpipelined loop." projectName="SIFT" solutionName="solution1" date="2018-12-05T18:35:12.408+0800" type="Warning"/>
        <logs message="WARNING: [HLS 200-433] Loop - Loop 1 has an initiation interval that is equal to the pipeline depth (1) - this results in an unpipelined loop." projectName="SIFT" solutionName="solution1" date="2018-12-05T18:35:06.257+0800" type="Warning"/>
        <logs message="WARNING: [RTGEN 206-101] RTL name 'SIFT2_Core_mux_83Zio' is changed to 'SIFT2_Core_mux_83Zio_x_x' due to conflict." projectName="SIFT" solutionName="solution1" date="2018-12-05T18:34:59.654+0800" type="Warning"/>
        <logs message="WARNING: [RTGEN 206-101] RTL name 'SIFT2_Core_mux_63VhK' is changed to 'SIFT2_Core_mux_63VhK_x_x' due to conflict." projectName="SIFT" solutionName="solution1" date="2018-12-05T18:34:50.190+0800" type="Warning"/>
        <logs message="WARNING: [HLS 200-433] Loop   ++ Loop 1.2 has an initiation interval that is equal to the pipeline depth (2) - this results in an unpipelined loop." projectName="SIFT" solutionName="solution1" date="2018-12-05T18:34:25.525+0800" type="Warning"/>
        <logs message="WARNING: [HLS 200-433] Loop  + Loop 1.1 has an initiation interval that is equal to the pipeline depth (1) - this results in an unpipelined loop." projectName="SIFT" solutionName="solution1" date="2018-12-05T18:34:23.467+0800" type="Warning"/>
        <logs message="WARNING: [HLS 200-433] Loop   ++ Loop 1.2 has an initiation interval that is equal to the pipeline depth (2) - this results in an unpipelined loop." projectName="SIFT" solutionName="solution1" date="2018-12-05T18:34:23.448+0800" type="Warning"/>
        <logs message="WARNING: [HLS 200-433] Loop  + Loop 1.1 has an initiation interval that is equal to the pipeline depth (1) - this results in an unpipelined loop." projectName="SIFT" solutionName="solution1" date="2018-12-05T18:34:23.342+0800" type="Warning"/>
        <logs message="WARNING: [RTGEN 206-101] RTL name 'SIFT2_Core_mux_83Zio' is changed to 'SIFT2_Core_mux_83Zio_x' due to conflict." projectName="SIFT" solutionName="solution1" date="2018-12-05T18:34:20.393+0800" type="Warning"/>
        <logs message="WARNING: [RTGEN 206-101] RTL name 'SIFT2_Core_mux_63VhK' is changed to 'SIFT2_Core_mux_63VhK_x' due to conflict." projectName="SIFT" solutionName="solution1" date="2018-12-05T18:34:18.285+0800" type="Warning"/>
        <logs message="WARNING: [HLS 200-433] Loop - loop_wait_for_start has an initiation interval that is equal to the pipeline depth (1) - this results in an unpipelined loop." projectName="SIFT" solutionName="solution1" date="2018-12-05T18:32:37.236+0800" type="Warning"/>
        <logs message="WARNING: [HLS 200-433] Loop - loop_wait_for_start has an initiation interval that is equal to the pipeline depth (1) - this results in an unpipelined loop." projectName="SIFT" solutionName="solution1" date="2018-12-05T18:32:36.964+0800" type="Warning"/>
        <logs message="WARNING: [HLS 200-433] Loop - loop_wait_for_start has an initiation interval that is equal to the pipeline depth (1) - this results in an unpipelined loop." projectName="SIFT" solutionName="solution1" date="2018-12-05T18:32:36.102+0800" type="Warning"/>
        <logs message="WARNING: [HLS 200-433] Loop - loop_wait_for_start has an initiation interval that is equal to the pipeline depth (1) - this results in an unpipelined loop." projectName="SIFT" solutionName="solution1" date="2018-12-05T18:32:35.843+0800" type="Warning"/>
        <logs message="WARNING: [HLS 200-433] Loop - Loop 1 has an initiation interval that is equal to the pipeline depth (1) - this results in an unpipelined loop." projectName="SIFT" solutionName="solution1" date="2018-12-05T18:30:36.359+0800" type="Warning"/>
        <logs message="WARNING: [HLS 200-433] Loop - Loop 1 has an initiation interval that is equal to the pipeline depth (1) - this results in an unpipelined loop." projectName="SIFT" solutionName="solution1" date="2018-12-05T18:30:31.583+0800" type="Warning"/>
        <logs message="WARNING: [HLS 200-433] Loop   ++ Loop 1.2 has an initiation interval that is equal to the pipeline depth (2) - this results in an unpipelined loop." projectName="SIFT" solutionName="solution1" date="2018-12-05T18:29:52.281+0800" type="Warning"/>
        <logs message="WARNING: [HLS 200-433] Loop  + Loop 1.1 has an initiation interval that is equal to the pipeline depth (1) - this results in an unpipelined loop." projectName="SIFT" solutionName="solution1" date="2018-12-05T18:29:51.626+0800" type="Warning"/>
        <logs message="WARNING: [HLS 200-433] Loop   ++ Loop 1.2 has an initiation interval that is equal to the pipeline depth (2) - this results in an unpipelined loop." projectName="SIFT" solutionName="solution1" date="2018-12-05T18:29:51.194+0800" type="Warning"/>
        <logs message="WARNING: [HLS 200-433] Loop  + Loop 1.1 has an initiation interval that is equal to the pipeline depth (1) - this results in an unpipelined loop." projectName="SIFT" solutionName="solution1" date="2018-12-05T18:29:50.685+0800" type="Warning"/>
        <logs message="WARNING: [HLS 200-433] Loop - loop_wait_for_start has an initiation interval that is equal to the pipeline depth (1) - this results in an unpipelined loop." projectName="SIFT" solutionName="solution1" date="2018-12-05T18:27:56.543+0800" type="Warning"/>
        <logs message="WARNING: [HLS 200-433] Loop - loop_wait_for_start has an initiation interval that is equal to the pipeline depth (1) - this results in an unpipelined loop." projectName="SIFT" solutionName="solution1" date="2018-12-05T18:27:56.090+0800" type="Warning"/>
        <logs message="WARNING: [HLS 200-433] Loop - loop_wait_for_start has an initiation interval that is equal to the pipeline depth (1) - this results in an unpipelined loop." projectName="SIFT" solutionName="solution1" date="2018-12-05T18:27:55.385+0800" type="Warning"/>
        <logs message="WARNING: [HLS 200-433] Loop - loop_wait_for_start has an initiation interval that is equal to the pipeline depth (1) - this results in an unpipelined loop." projectName="SIFT" solutionName="solution1" date="2018-12-05T18:27:54.774+0800" type="Warning"/>
        <logs message="WARNING: [SYN 201-103] Legalizing function name 'Mat2AXIvideo.1' to 'Mat2AXIvideo_1'." projectName="SIFT" solutionName="solution1" date="2018-12-05T18:27:53.255+0800" type="Warning"/>
        <logs message="WARNING: [SYN 201-103] Legalizing function name 'Array2D2Mat.1' to 'Array2D2Mat_1'." projectName="SIFT" solutionName="solution1" date="2018-12-05T18:27:52.961+0800" type="Warning"/>
        <logs message="WARNING: [SYN 201-103] Legalizing function name 'Result2Array2D&lt;511>.1' to 'Result2Array2D_511_1'." projectName="SIFT" solutionName="solution1" date="2018-12-05T18:27:52.951+0800" type="Warning"/>
        <logs message="WARNING: [SYN 201-103] Legalizing function name 'Result2Array2D&lt;511>' to 'Result2Array2D_511_s'." projectName="SIFT" solutionName="solution1" date="2018-12-05T18:27:52.939+0800" type="Warning"/>
        <logs message="WARNING: [SYN 201-103] Legalizing function name 'match&lt;511>' to 'match_511_s'." projectName="SIFT" solutionName="solution1" date="2018-12-05T18:27:52.930+0800" type="Warning"/>
        <logs message="WARNING: [SYN 201-103] Legalizing function name 'sqrt_fixed&lt;32, 32>' to 'sqrt_fixed_32_32_s'." projectName="SIFT" solutionName="solution1" date="2018-12-05T18:27:52.913+0800" type="Warning"/>
        <logs message="WARNING: [SYN 201-103] Legalizing function name 'sin_or_cos&lt;float>' to 'sin_or_cos_float_s'." projectName="SIFT" solutionName="solution1" date="2018-12-05T18:27:52.899+0800" type="Warning"/>
        <logs message="WARNING: [SYN 201-103] Legalizing function name 'atan2_cordic&lt;float>' to 'atan2_cordic_float_s'." projectName="SIFT" solutionName="solution1" date="2018-12-05T18:27:52.888+0800" type="Warning"/>
        <logs message="WARNING: [SYN 201-103] Legalizing function name 'atan2_generic&lt;float>' to 'atan2_generic_float_s'." projectName="SIFT" solutionName="solution1" date="2018-12-05T18:27:52.875+0800" type="Warning"/>
        <logs message="WARNING: [SYN 201-103] Legalizing function name 'addsub.2' to 'addsub_2'." projectName="SIFT" solutionName="solution1" date="2018-12-05T18:27:52.863+0800" type="Warning"/>
        <logs message="WARNING: [SYN 201-103] Legalizing function name 'addsub.1' to 'addsub_1'." projectName="SIFT" solutionName="solution1" date="2018-12-05T18:27:52.852+0800" type="Warning"/>
        <logs message="WARNING: [SYN 201-103] Legalizing function name 'solve&lt;ap_fixed >' to 'solve_ap_fixed_s'." projectName="SIFT" solutionName="solution1" date="2018-12-05T18:27:52.841+0800" type="Warning"/>
        <logs message="WARNING: [SYN 201-103] Legalizing function name 'sqrt_fixed&lt;32, 16>' to 'sqrt_fixed_32_16_s'." projectName="SIFT" solutionName="solution1" date="2018-12-05T18:27:52.832+0800" type="Warning"/>
        <logs message="WARNING: [SYN 201-103] Legalizing function name 'pow_generic&lt;float>' to 'pow_generic_float_s'." projectName="SIFT" solutionName="solution1" date="2018-12-05T18:27:52.824+0800" type="Warning"/>
        <logs message="WARNING: [SYN 201-103] Legalizing function name 'Block_Mat.exit412_pr' to 'Block_Mat_exit412_pr'." projectName="SIFT" solutionName="solution1" date="2018-12-05T18:27:52.813+0800" type="Warning"/>
        <logs message="WARNING: [ANALYSIS 214-52] Found false inter dependency for variable 'LineBuffer.val[1].V' (./imgproc.h:89)." projectName="SIFT" solutionName="solution1" date="2018-12-05T18:27:52.777+0800" type="Warning"/>
        <logs message="WARNING: [ANALYSIS 214-52] Found false inter dependency for variable 'LineBuffer.val[11].V' (./imgproc.h:89)." projectName="SIFT" solutionName="solution1" date="2018-12-05T18:27:16.762+0800" type="Warning"/>
        <logs message="WARNING: [ANALYSIS 214-52] Found false inter dependency for variable 'LineBuffer.val[9].V' (./imgproc.h:89)." projectName="SIFT" solutionName="solution1" date="2018-12-05T18:27:16.750+0800" type="Warning"/>
        <logs message="WARNING: [ANALYSIS 214-52] Found false inter dependency for variable 'LineBuffer.val[2].V' (./imgproc.h:89)." projectName="SIFT" solutionName="solution1" date="2018-12-05T18:27:16.739+0800" type="Warning"/>
        <logs message="WARNING: [ANALYSIS 214-52] Found false inter dependency for variable 'LineBuffer.val[13].V' (./imgproc.h:89)." projectName="SIFT" solutionName="solution1" date="2018-12-05T18:27:16.729+0800" type="Warning"/>
        <logs message="WARNING: [ANALYSIS 214-52] Found false inter dependency for variable 'LineBuffer.val[10].V' (./imgproc.h:89)." projectName="SIFT" solutionName="solution1" date="2018-12-05T18:27:16.719+0800" type="Warning"/>
        <logs message="WARNING: [ANALYSIS 214-52] Found false inter dependency for variable 'LineBuffer.val[14].V' (./imgproc.h:89)." projectName="SIFT" solutionName="solution1" date="2018-12-05T18:27:16.710+0800" type="Warning"/>
        <logs message="WARNING: [ANALYSIS 214-52] Found false inter dependency for variable 'LineBuffer.val[7].V' (./imgproc.h:89)." projectName="SIFT" solutionName="solution1" date="2018-12-05T18:27:16.700+0800" type="Warning"/>
        <logs message="WARNING: [ANALYSIS 214-52] Found false inter dependency for variable 'LineBuffer.val[5].V' (./imgproc.h:89)." projectName="SIFT" solutionName="solution1" date="2018-12-05T18:27:16.688+0800" type="Warning"/>
        <logs message="WARNING: [ANALYSIS 214-52] Found false inter dependency for variable 'LineBuffer.val[3].V' (./imgproc.h:89)." projectName="SIFT" solutionName="solution1" date="2018-12-05T18:27:16.674+0800" type="Warning"/>
        <logs message="WARNING: [ANALYSIS 214-52] Found false inter dependency for variable 'LineBuffer.val[12].V' (./imgproc.h:89)." projectName="SIFT" solutionName="solution1" date="2018-12-05T18:27:16.664+0800" type="Warning"/>
        <logs message="WARNING: [ANALYSIS 214-52] Found false inter dependency for variable 'LineBuffer.val[8].V' (./imgproc.h:89)." projectName="SIFT" solutionName="solution1" date="2018-12-05T18:27:16.654+0800" type="Warning"/>
        <logs message="WARNING: [ANALYSIS 214-52] Found false inter dependency for variable 'LineBuffer.val[6].V' (./imgproc.h:89)." projectName="SIFT" solutionName="solution1" date="2018-12-05T18:27:16.640+0800" type="Warning"/>
        <logs message="WARNING: [ANALYSIS 214-52] Found false inter dependency for variable 'LineBuffer.val[4].V' (./imgproc.h:89)." projectName="SIFT" solutionName="solution1" date="2018-12-05T18:27:16.630+0800" type="Warning"/>
        <logs message="WARNING: [ANALYSIS 214-52] Found false inter dependency for variable 'dst[5].val.V'." projectName="SIFT" solutionName="solution1" date="2018-12-05T18:27:16.623+0800" type="Warning"/>
        <logs message="WARNING: [ANALYSIS 214-52] Found false inter dependency for variable 'src[1].val.V'." projectName="SIFT" solutionName="solution1" date="2018-12-05T18:27:16.559+0800" type="Warning"/>
        <logs message="WARNING: [ANALYSIS 214-52] Found false inter dependency for variable 'src[3].val.V'." projectName="SIFT" solutionName="solution1" date="2018-12-05T18:27:16.544+0800" type="Warning"/>
        <logs message="WARNING: [ANALYSIS 214-52] Found false inter dependency for variable 'src[0].val.V'." projectName="SIFT" solutionName="solution1" date="2018-12-05T18:27:16.530+0800" type="Warning"/>
        <logs message="WARNING: [ANALYSIS 214-52] Found false inter dependency for variable 'src[4].val.V'." projectName="SIFT" solutionName="solution1" date="2018-12-05T18:27:16.519+0800" type="Warning"/>
        <logs message="WARNING: [ANALYSIS 214-52] Found false inter dependency for variable 'src[2].val.V'." projectName="SIFT" solutionName="solution1" date="2018-12-05T18:27:16.502+0800" type="Warning"/>
        <logs message="WARNING: [ANALYSIS 214-52] Found false inter dependency for variable 'LineBuffer.val[10]' (./imgproc.h:89)." projectName="SIFT" solutionName="solution1" date="2018-12-05T18:27:16.484+0800" type="Warning"/>
        <logs message="WARNING: [ANALYSIS 214-52] Found false inter dependency for variable 'LineBuffer.val[6]' (./imgproc.h:89)." projectName="SIFT" solutionName="solution1" date="2018-12-05T18:27:16.402+0800" type="Warning"/>
        <logs message="WARNING: [ANALYSIS 214-52] Found false inter dependency for variable 'LineBuffer.val[2]' (./imgproc.h:89)." projectName="SIFT" solutionName="solution1" date="2018-12-05T18:27:16.389+0800" type="Warning"/>
        <logs message="WARNING: [ANALYSIS 214-52] Found false inter dependency for variable 'LineBuffer.val[12]' (./imgproc.h:89)." projectName="SIFT" solutionName="solution1" date="2018-12-05T18:27:16.378+0800" type="Warning"/>
        <logs message="WARNING: [ANALYSIS 214-52] Found false inter dependency for variable 'LineBuffer.val[13]' (./imgproc.h:89)." projectName="SIFT" solutionName="solution1" date="2018-12-05T18:27:16.368+0800" type="Warning"/>
        <logs message="WARNING: [ANALYSIS 214-52] Found false inter dependency for variable 'LineBuffer.val[4]' (./imgproc.h:89)." projectName="SIFT" solutionName="solution1" date="2018-12-05T18:27:16.358+0800" type="Warning"/>
        <logs message="WARNING: [ANALYSIS 214-52] Found false inter dependency for variable 'LineBuffer.val[5]' (./imgproc.h:89)." projectName="SIFT" solutionName="solution1" date="2018-12-05T18:27:16.350+0800" type="Warning"/>
        <logs message="WARNING: [ANALYSIS 214-52] Found false inter dependency for variable 'LineBuffer.val[8]' (./imgproc.h:89)." projectName="SIFT" solutionName="solution1" date="2018-12-05T18:27:16.340+0800" type="Warning"/>
        <logs message="WARNING: [ANALYSIS 214-52] Found false inter dependency for variable 'LineBuffer.val[7]' (./imgproc.h:89)." projectName="SIFT" solutionName="solution1" date="2018-12-05T18:27:16.330+0800" type="Warning"/>
        <logs message="WARNING: [ANALYSIS 214-52] Found false inter dependency for variable 'LineBuffer.val[3]' (./imgproc.h:89)." projectName="SIFT" solutionName="solution1" date="2018-12-05T18:27:16.321+0800" type="Warning"/>
        <logs message="WARNING: [ANALYSIS 214-52] Found false inter dependency for variable 'LineBuffer.val[11]' (./imgproc.h:89)." projectName="SIFT" solutionName="solution1" date="2018-12-05T18:27:16.311+0800" type="Warning"/>
        <logs message="WARNING: [ANALYSIS 214-52] Found false inter dependency for variable 'LineBuffer.val[9]' (./imgproc.h:89)." projectName="SIFT" solutionName="solution1" date="2018-12-05T18:27:16.301+0800" type="Warning"/>
        <logs message="WARNING: [ANALYSIS 214-52] Found false inter dependency for variable 'LineBuffer.val[1]' (./imgproc.h:89)." projectName="SIFT" solutionName="solution1" date="2018-12-05T18:27:16.292+0800" type="Warning"/>
        <logs message="WARNING: [ANALYSIS 214-52] Found false inter dependency for variable 'LineBuffer.val[14]' (./imgproc.h:89)." projectName="SIFT" solutionName="solution1" date="2018-12-05T18:27:16.283+0800" type="Warning"/>
        <logs message="WARNING: [ANALYSIS 214-52] Found false inter dependency for variable 'dst.val.V'." projectName="SIFT" solutionName="solution1" date="2018-12-05T18:27:16.273+0800" type="Warning"/>
        <logs message="WARNING: [ANALYSIS 214-52] Found false inter dependency for variable 'src.val'." projectName="SIFT" solutionName="solution1" date="2018-12-05T18:27:16.263+0800" type="Warning"/>
        <logs message="WARNING: [XFORM 203-631] Renaming function 'Block_Mat.exit412_proc689' to 'Block_Mat.exit412_pr' (image_core.cpp:27)" projectName="SIFT" solutionName="solution1" date="2018-12-05T18:27:16.254+0800" type="Warning"/>
        <logs message="WARNING: [XFORM 203-631] Renaming function 'cordic_::addsub&lt;0, 0, ap_fixed&lt;40, 1, (ap_q_mode)5, (ap_o_mode)3, 0>, ap_fixed&lt;40, 1, (ap_q_mode)0, (ap_o_mode)3, 0>, ap_uint&lt;1> >' to 'addsub.2' (r:/builds/2018.2/continuous/2018_06_14_2258646/src/products/hls/hls_lib/hlsmath/include/FloatingPoint\hls_cordic.h:122:5)" projectName="SIFT" solutionName="solution1" date="2018-12-05T18:27:11.974+0800" type="Warning"/>
        <logs message="WARNING: [XFORM 203-631] Renaming function 'cordic_::addsub&lt;0, 0, ap_fixed&lt;43, 4, (ap_q_mode)5, (ap_o_mode)3, 0>, ap_fixed&lt;43, 4, (ap_q_mode)5, (ap_o_mode)3, 0>, ap_uint&lt;1> >' to 'addsub.1' (r:/builds/2018.2/continuous/2018_06_14_2258646/src/products/hls/hls_lib/hlsmath/include/FloatingPoint\hls_cordic.h:122:5)" projectName="SIFT" solutionName="solution1" date="2018-12-05T18:27:11.965+0800" type="Warning"/>
        <logs message="WARNING: [XFORM 203-631] Renaming function 'cordic_::addsub&lt;0, 0, ap_fixed&lt;43, 4, (ap_q_mode)5, (ap_o_mode)3, 0>, ap_fixed&lt;43, 4, (ap_q_mode)5, (ap_o_mode)3, 0>, bool>' to 'addsub' (r:/builds/2018.2/continuous/2018_06_14_2258646/src/products/hls/hls_lib/hlsmath/include/FloatingPoint\hls_cordic.h:122:5)" projectName="SIFT" solutionName="solution1" date="2018-12-05T18:27:11.955+0800" type="Warning"/>
        <logs message="WARNING: [XFORM 203-631] Renaming function 'cordic_::atan2_cordic&lt;float>' to 'atan2_cordic&lt;float>' (r:/builds/2018.2/continuous/2018_06_14_2258646/src/products/hls/hls_lib/hlsmath/include/FloatingPoint\hls_cordic.h:749)" projectName="SIFT" solutionName="solution1" date="2018-12-05T18:27:11.945+0800" type="Warning"/>
        <logs message="WARNING: [XFORM 203-631] Renaming function 'cordic_::atan2_generic&lt;float>' to 'atan2_generic&lt;float>' (r:/builds/2018.2/continuous/2018_06_14_2258646/src/products/hls/hls_lib/hlsmath/include/FloatingPoint\hls_cordic.h:672)" projectName="SIFT" solutionName="solution1" date="2018-12-05T18:27:11.933+0800" type="Warning"/>
        <logs message="WARNING: [XFORM 203-631] Renaming function 'hls::AXIvideo2Mat&lt;8, 256, 256, 0>' to 'AXIvideo2Mat' (E:/Xilinx/Vivado/2018.2/common/technology/autopilot/hls/hls_video_io.h:63:9)" projectName="SIFT" solutionName="solution1" date="2018-12-05T18:27:11.922+0800" type="Warning"/>
        <logs message="WARNING: [XFORM 203-631] Renaming function 'hls::AXIvideo2Mat&lt;8, 256, 256, 0>616' to 'AXIvideo2Mat616' (E:/Xilinx/Vivado/2018.2/common/technology/autopilot/hls/hls_video_io.h:63:9)" projectName="SIFT" solutionName="solution1" date="2018-12-05T18:27:11.913+0800" type="Warning"/>
        <logs message="WARNING: [XFORM 203-631] Renaming function 'hls::Array2D2Mat&lt;16, 128, unsigned char, 0>' to 'Array2D2Mat.1' (./type.h:361:22)" projectName="SIFT" solutionName="solution1" date="2018-12-05T18:27:11.902+0800" type="Warning"/>
        <logs message="WARNING: [XFORM 203-631] Renaming function 'hls::Array2D2Mat&lt;32, 128, unsigned char, 0>' to 'Array2D2Mat' (./type.h:361:22)" projectName="SIFT" solutionName="solution1" date="2018-12-05T18:27:11.890+0800" type="Warning"/>
        <logs message="WARNING: [XFORM 203-631] Renaming function 'hls::Filter2D&lt;256, 256, ap_fixed&lt;32, 16, (ap_q_mode)5, (ap_o_mode)3, 0>, ap_fixed&lt;32, 16, (ap_q_mode)5, (ap_o_mode)3, 0>, 15, 15, ap_fixed&lt;32, 10, (ap_q_mode)1, (ap_o_mode)3, 0> >' to 'Filter2D' (./imgproc.h:89:4)" projectName="SIFT" solutionName="solution1" date="2018-12-05T18:27:11.876+0800" type="Warning"/>
        <logs message="WARNING: [XFORM 203-631] Renaming function 'hls::Filter2D&lt;256, 256, unsigned char, ap_fixed&lt;32, 16, (ap_q_mode)5, (ap_o_mode)3, 0>, 15, 15, ap_fixed&lt;32, 10, (ap_q_mode)1, (ap_o_mode)3, 0> >16' to 'Filter2D16' (./imgproc.h:89:27)" projectName="SIFT" solutionName="solution1" date="2018-12-05T18:27:11.866+0800" type="Warning"/>
        <logs message="WARNING: [XFORM 203-631] Renaming function 'hls::GaussianBlur&lt;15, 15, 256, 256, ap_fixed&lt;32, 16, (ap_q_mode)5, (ap_o_mode)3, 0>, ap_fixed&lt;32, 16, (ap_q_mode)5, (ap_o_mode)3, 0> >' to 'GaussianBlur' (./imgproc.h:188:1)" projectName="SIFT" solutionName="solution1" date="2018-12-05T18:27:11.822+0800" type="Warning"/>
        <logs message="WARNING: [XFORM 203-631] Renaming function 'hls::GaussianBlur&lt;15, 15, 256, 256, unsigned char, ap_fixed&lt;32, 16, (ap_q_mode)5, (ap_o_mode)3, 0> >15' to 'GaussianBlur15' (./imgproc.h:188:1)" projectName="SIFT" solutionName="solution1" date="2018-12-05T18:27:11.798+0800" type="Warning"/>
        <logs message="WARNING: [XFORM 203-631] Renaming function 'hls::Mat2AXIvideo&lt;8, 16, 128, 0>' to 'Mat2AXIvideo.1' (E:/Xilinx/Vivado/2018.2/common/technology/autopilot/hls/hls_video_io.h:125:50)" projectName="SIFT" solutionName="solution1" date="2018-12-05T18:27:11.790+0800" type="Warning"/>
        <logs message="WARNING: [XFORM 203-631] Renaming function 'hls::Mat2AXIvideo&lt;8, 32, 128, 0>' to 'Mat2AXIvideo' (E:/Xilinx/Vivado/2018.2/common/technology/autopilot/hls/hls_video_io.h:125:50)" projectName="SIFT" solutionName="solution1" date="2018-12-05T18:27:11.778+0800" type="Warning"/>
        <logs message="WARNING: [XFORM 203-631] Renaming function 'hls::Mat2Array2D&lt;256, 256, 0, unsigned char>' to 'Mat2Array2D' (./type.h:286:21)" projectName="SIFT" solutionName="solution1" date="2018-12-05T18:27:11.766+0800" type="Warning"/>
        <logs message="WARNING: [XFORM 203-631] Renaming function 'hls::Mat2Array2D&lt;256, 256, 0, unsigned char>617' to 'Mat2Array2D617' (./type.h:286:21)" projectName="SIFT" solutionName="solution1" date="2018-12-05T18:27:11.757+0800" type="Warning"/>
        <logs message="WARNING: [XFORM 203-631] Renaming function 'hls::Resize&lt;256, 256, 256, 256, ap_fixed&lt;32, 16, (ap_q_mode)5, (ap_o_mode)3, 0>, ap_fixed&lt;32, 16, (ap_q_mode)5, (ap_o_mode)3, 0> >' to 'Resize' (./imgproc.h:14:26)" projectName="SIFT" solutionName="solution1" date="2018-12-05T18:27:11.748+0800" type="Warning"/>
        <logs message="WARNING: [XFORM 203-631] Renaming function 'hls::Result2Array2D&lt;511>' to 'Result2Array2D&lt;511>' (./sift.h:969)" projectName="SIFT" solutionName="solution1" date="2018-12-05T18:27:11.738+0800" type="Warning"/>
        <logs message="WARNING: [XFORM 203-631] Renaming function 'hls::Result2Array2D&lt;511>.1' to 'Result2Array2D&lt;511>.1' (./sift.h:804:6)" projectName="SIFT" solutionName="solution1" date="2018-12-05T18:27:11.727+0800" type="Warning"/>
        <logs message="WARNING: [XFORM 203-631] Renaming function 'hls::SubArray2D&lt;256, 256, ap_fixed&lt;32, 16, (ap_q_mode)5, (ap_o_mode)3, 0>, ap_fixed&lt;32, 16, (ap_q_mode)5, (ap_o_mode)3, 0> >' to 'SubArray2D' (./type.h:456:22)" projectName="SIFT" solutionName="solution1" date="2018-12-05T18:27:11.715+0800" type="Warning"/>
        <logs message="WARNING: [XFORM 203-631] Renaming function 'hls::adjustLocalExtrema&lt;256, 256, ap_fixed&lt;32, 16, (ap_q_mode)5, (ap_o_mode)3, 0>, ap_fixed&lt;32, 16, (ap_q_mode)5, (ap_o_mode)3, 0> >' to 'adjustLocalExtrema' (./sift.h:6:34)" projectName="SIFT" solutionName="solution1" date="2018-12-05T18:27:11.706+0800" type="Warning"/>
        <logs message="WARNING: [XFORM 203-631] Renaming function 'hls::buildDoGPyramid&lt;256, 256, ap_fixed&lt;32, 16, (ap_q_mode)5, (ap_o_mode)3, 0>, ap_fixed&lt;32, 16, (ap_q_mode)5, (ap_o_mode)3, 0> >' to 'buildDoGPyramid' (./sift.h:150:3)" projectName="SIFT" solutionName="solution1" date="2018-12-05T18:27:11.696+0800" type="Warning"/>
        <logs message="WARNING: [XFORM 203-631] Renaming function 'hls::buildGaussianPyramid&lt;256, 256, ap_fixed&lt;32, 16, (ap_q_mode)5, (ap_o_mode)3, 0>, ap_fixed&lt;32, 16, (ap_q_mode)5, (ap_o_mode)3, 0>, ap_fixed&lt;32, 16, (ap_q_mode)5, (ap_o_mode)3, 0> >' to 'buildGaussianPyramid' (./type.h:6:21)" projectName="SIFT" solutionName="solution1" date="2018-12-05T18:27:11.653+0800" type="Warning"/>
        <logs message="WARNING: [XFORM 203-631] Renaming function 'hls::calcOrientationHist&lt;256, 256, ap_fixed&lt;32, 16, (ap_q_mode)5, (ap_o_mode)3, 0>, ap_fixed&lt;32, 16, (ap_q_mode)5, (ap_o_mode)3, 0> >' to 'calcOrientationHist' (./sift.h:5:34)" projectName="SIFT" solutionName="solution1" date="2018-12-05T18:27:11.643+0800" type="Warning"/>
        <logs message="WARNING: [XFORM 203-631] Renaming function 'hls::calcSIFTDescriptor&lt;256, 256, ap_fixed&lt;32, 16, (ap_q_mode)5, (ap_o_mode)3, 0>, ap_fixed&lt;32, 16, (ap_q_mode)5, (ap_o_mode)3, 0> >12' to 'calcSIFTDescriptor12' (./sift.h:5:35)" projectName="SIFT" solutionName="solution1" date="2018-12-05T18:27:11.632+0800" type="Warning"/>
        <logs message="WARNING: [XFORM 203-631] Renaming function 'hls::compute&lt;4, 511, 256, 256, unsigned char, ap_fixed&lt;32, 16, (ap_q_mode)5, (ap_o_mode)3, 0> >' to 'compute' (./sift.h:761:18)" projectName="SIFT" solutionName="solution1" date="2018-12-05T18:27:11.616+0800" type="Warning"/>
        <logs message="WARNING: [XFORM 203-631] Renaming function 'hls::detect&lt;4, 511, 256, 256, unsigned char, ap_fixed&lt;32, 16, (ap_q_mode)5, (ap_o_mode)3, 0> >' to 'detect' (./sift.h:6:25)" projectName="SIFT" solutionName="solution1" date="2018-12-05T18:27:11.595+0800" type="Warning"/>
        <logs message="WARNING: [XFORM 203-631] Renaming function 'hls::findScaleSpaceExtrema&lt;511, 256, 256, ap_fixed&lt;32, 16, (ap_q_mode)5, (ap_o_mode)3, 0>, ap_fixed&lt;32, 16, (ap_q_mode)5, (ap_o_mode)3, 0> >' to 'findScaleSpaceExtrem' (./sift.h:14:25)" projectName="SIFT" solutionName="solution1" date="2018-12-05T18:27:11.585+0800" type="Warning"/>
        <logs message="WARNING: [XFORM 203-631] Renaming function 'hls::getGaussianKernel&lt;15, 15, ap_fixed&lt;32, 10, (ap_q_mode)1, (ap_o_mode)3, 0>, float>' to 'getGaussianKernel' (./imgproc.h:15:4)" projectName="SIFT" solutionName="solution1" date="2018-12-05T18:27:11.575+0800" type="Warning"/>
        <logs message="WARNING: [XFORM 203-631] Renaming function 'hls::match&lt;511>' to 'match&lt;511>' (./sift.h:619)" projectName="SIFT" solutionName="solution1" date="2018-12-05T18:27:11.558+0800" type="Warning"/>
        <logs message="WARNING: [XFORM 203-631] Renaming function 'hls::solve&lt;ap_fixed&lt;32, 16, (ap_q_mode)5, (ap_o_mode)3, 0> >' to 'solve&lt;ap_fixed >' (./sift.h:181:2)" projectName="SIFT" solutionName="solution1" date="2018-12-05T18:27:11.547+0800" type="Warning"/>
        <logs message="WARNING: [XFORM 203-631] Renaming function 'hotbm_::sin_or_cos&lt;float>' to 'sin_or_cos&lt;float>' (r:/builds/2018.2/continuous/2018_06_14_2258646/src/products/hls/hls_lib/hlsmath/include/FloatingPoint\hls_hotbm.h:235)" projectName="SIFT" solutionName="solution1" date="2018-12-05T18:27:11.538+0800" type="Warning"/>
        <logs message="WARNING: [XFORM 203-631] Renaming function 'pow_reduce::pow_generic&lt;float>' to 'pow_generic&lt;float>' (r:/builds/2018.2/continuous/2018_06_14_2258646/src/products/hls/hls_lib/hlsmath/include/FloatingPoint\hls_pow.h:313)" projectName="SIFT" solutionName="solution1" date="2018-12-05T18:27:11.528+0800" type="Warning"/>
        <logs message="WARNING: [XFORM 203-631] Renaming function 'scaled_fixed2ieee&lt;29, 1>' to 'scaled_fixed2ieee' (r:/builds/2018.2/continuous/2018_06_14_2258646/src/products/hls/src/technology/autopilot/header_files\utils/x_hls_float_utils.h:109:37)" projectName="SIFT" solutionName="solution1" date="2018-12-05T18:27:11.519+0800" type="Warning"/>
        <logs message="WARNING: [XFORM 203-713] All the elements of global array 'dst1.val' should be updated in process function 'hls::Result2Array2D&lt;511>.1', otherwise it may not be synthesized correctly." projectName="SIFT" solutionName="solution1" date="2018-12-05T18:26:08.756+0800" type="Warning"/>
        <logs message="WARNING: [XFORM 203-713] All the elements of global array 'dst0.val' should be updated in process function 'hls::Result2Array2D&lt;511>', otherwise it may not be synthesized correctly." projectName="SIFT" solutionName="solution1" date="2018-12-05T18:26:08.568+0800" type="Warning"/>
        <logs message="WARNING: [XFORM 203-713] All the elements of global array 'matches.val.idx1' should be updated in process function 'hls::compute&lt;4, 511, 256, 256, unsigned char, ap_fixed&lt;32, 16, (ap_q_mode)5, (ap_o_mode)3, 0> >', otherwise it may not be synthesized correctly." projectName="SIFT" solutionName="solution1" date="2018-12-05T18:26:08.557+0800" type="Warning"/>
        <logs message="WARNING: [XFORM 203-713] All the elements of global array 'matches.val.idx0' should be updated in process function 'hls::compute&lt;4, 511, 256, 256, unsigned char, ap_fixed&lt;32, 16, (ap_q_mode)5, (ap_o_mode)3, 0> >', otherwise it may not be synthesized correctly." projectName="SIFT" solutionName="solution1" date="2018-12-05T18:26:08.537+0800" type="Warning"/>
        <logs message="WARNING: [XFORM 203-713] All the elements of global array 'descriptors1.val.val' should be updated in process function 'hls::compute&lt;4, 511, 256, 256, unsigned char, ap_fixed&lt;32, 16, (ap_q_mode)5, (ap_o_mode)3, 0> >', otherwise it may not be synthesized correctly." projectName="SIFT" solutionName="solution1" date="2018-12-05T18:26:08.525+0800" type="Warning"/>
        <logs message="WARNING: [XFORM 203-713] All the elements of global array 'descriptors0.val.val' should be updated in process function 'hls::compute&lt;4, 511, 256, 256, unsigned char, ap_fixed&lt;32, 16, (ap_q_mode)5, (ap_o_mode)3, 0> >', otherwise it may not be synthesized correctly." projectName="SIFT" solutionName="solution1" date="2018-12-05T18:26:08.515+0800" type="Warning"/>
        <logs message="WARNING: [XFORM 203-713] All the elements of global array 'keypoints1.val.layer'  should be updated in process function 'hls::compute&lt;4, 511, 256, 256, unsigned char, ap_fixed&lt;32, 16, (ap_q_mode)5, (ap_o_mode)3, 0> >', otherwise it may not be synthesized correctly." projectName="SIFT" solutionName="solution1" date="2018-12-05T18:26:08.507+0800" type="Warning"/>
        <logs message="WARNING: [XFORM 203-713] All the elements of global array 'keypoints1.val.octave'  should be updated in process function 'hls::compute&lt;4, 511, 256, 256, unsigned char, ap_fixed&lt;32, 16, (ap_q_mode)5, (ap_o_mode)3, 0> >', otherwise it may not be synthesized correctly." projectName="SIFT" solutionName="solution1" date="2018-12-05T18:26:08.498+0800" type="Warning"/>
        <logs message="WARNING: [XFORM 203-713] All the elements of global array 'keypoints1.val.sigma.V'  should be updated in process function 'hls::compute&lt;4, 511, 256, 256, unsigned char, ap_fixed&lt;32, 16, (ap_q_mode)5, (ap_o_mode)3, 0> >', otherwise it may not be synthesized correctly." projectName="SIFT" solutionName="solution1" date="2018-12-05T18:26:08.489+0800" type="Warning"/>
        <logs message="WARNING: [XFORM 203-713] All the elements of global array 'keypoints1.val.angle.V'  should be updated in process function 'hls::compute&lt;4, 511, 256, 256, unsigned char, ap_fixed&lt;32, 16, (ap_q_mode)5, (ap_o_mode)3, 0> >', otherwise it may not be synthesized correctly." projectName="SIFT" solutionName="solution1" date="2018-12-05T18:26:08.481+0800" type="Warning"/>
        <logs message="WARNING: [XFORM 203-713] All the elements of global array 'keypoints1.val.pt.y' should be updated in process function 'hls::compute&lt;4, 511, 256, 256, unsigned char, ap_fixed&lt;32, 16, (ap_q_mode)5, (ap_o_mode)3, 0> >', otherwise it may not be synthesized correctly." projectName="SIFT" solutionName="solution1" date="2018-12-05T18:26:08.472+0800" type="Warning"/>
        <logs message="WARNING: [XFORM 203-713] All the elements of global array 'keypoints1.val.pt.x' should be updated in process function 'hls::compute&lt;4, 511, 256, 256, unsigned char, ap_fixed&lt;32, 16, (ap_q_mode)5, (ap_o_mode)3, 0> >', otherwise it may not be synthesized correctly." projectName="SIFT" solutionName="solution1" date="2018-12-05T18:26:08.463+0800" type="Warning"/>
        <logs message="WARNING: [XFORM 203-713] All the elements of global array 'keypoints0.val.layer'  should be updated in process function 'hls::compute&lt;4, 511, 256, 256, unsigned char, ap_fixed&lt;32, 16, (ap_q_mode)5, (ap_o_mode)3, 0> >', otherwise it may not be synthesized correctly." projectName="SIFT" solutionName="solution1" date="2018-12-05T18:26:08.454+0800" type="Warning"/>
        <logs message="WARNING: [XFORM 203-713] All the elements of global array 'keypoints0.val.octave'  should be updated in process function 'hls::compute&lt;4, 511, 256, 256, unsigned char, ap_fixed&lt;32, 16, (ap_q_mode)5, (ap_o_mode)3, 0> >', otherwise it may not be synthesized correctly." projectName="SIFT" solutionName="solution1" date="2018-12-05T18:26:08.446+0800" type="Warning"/>
        <logs message="WARNING: [XFORM 203-713] All the elements of global array 'keypoints0.val.sigma.V'  should be updated in process function 'hls::compute&lt;4, 511, 256, 256, unsigned char, ap_fixed&lt;32, 16, (ap_q_mode)5, (ap_o_mode)3, 0> >', otherwise it may not be synthesized correctly." projectName="SIFT" solutionName="solution1" date="2018-12-05T18:26:08.437+0800" type="Warning"/>
        <logs message="WARNING: [XFORM 203-713] All the elements of global array 'keypoints0.val.angle.V'  should be updated in process function 'hls::compute&lt;4, 511, 256, 256, unsigned char, ap_fixed&lt;32, 16, (ap_q_mode)5, (ap_o_mode)3, 0> >', otherwise it may not be synthesized correctly." projectName="SIFT" solutionName="solution1" date="2018-12-05T18:26:08.429+0800" type="Warning"/>
        <logs message="WARNING: [XFORM 203-713] All the elements of global array 'keypoints0.val.pt.y' should be updated in process function 'hls::compute&lt;4, 511, 256, 256, unsigned char, ap_fixed&lt;32, 16, (ap_q_mode)5, (ap_o_mode)3, 0> >', otherwise it may not be synthesized correctly." projectName="SIFT" solutionName="solution1" date="2018-12-05T18:26:08.421+0800" type="Warning"/>
        <logs message="WARNING: [XFORM 203-713] All the elements of global array 'keypoints0.val.pt.x' should be updated in process function 'hls::compute&lt;4, 511, 256, 256, unsigned char, ap_fixed&lt;32, 16, (ap_q_mode)5, (ap_o_mode)3, 0> >', otherwise it may not be synthesized correctly." projectName="SIFT" solutionName="solution1" date="2018-12-05T18:26:08.413+0800" type="Warning"/>
        <logs message="WARNING: [XFORM 203-713] All the elements of global array 'src1.val' should be updated in process function 'hls::Mat2Array2D&lt;256, 256, 0, unsigned char>', otherwise it may not be synthesized correctly." projectName="SIFT" solutionName="solution1" date="2018-12-05T18:26:08.404+0800" type="Warning"/>
        <logs message="WARNING: [XFORM 203-713] All the elements of global array 'src0.val' should be updated in process function 'hls::Mat2Array2D&lt;256, 256, 0, unsigned char>617', otherwise it may not be synthesized correctly." projectName="SIFT" solutionName="solution1" date="2018-12-05T18:26:08.395+0800" type="Warning"/>
        <logs message="WARNING: [XFORM 203-561] Updating loop lower bound from 0 to 16 for loop 'Loop-0' in function 'hls::Array2D2Mat&lt;16, 128, unsigned char, 0>'." projectName="SIFT" solutionName="solution1" date="2018-12-05T18:26:08.387+0800" type="Warning"/>
        <logs message="WARNING: [XFORM 203-561] Updating loop lower bound from 0 to 128 for loop 'Loop-0-0' in function 'hls::Array2D2Mat&lt;16, 128, unsigned char, 0>'." projectName="SIFT" solutionName="solution1" date="2018-12-05T18:25:55.883+0800" type="Warning"/>
        <logs message="WARNING: [XFORM 203-561] Updating loop lower bound from 0 to 32 for loop 'Loop-0' in function 'hls::Array2D2Mat&lt;32, 128, unsigned char, 0>'." projectName="SIFT" solutionName="solution1" date="2018-12-05T18:25:55.874+0800" type="Warning"/>
        <logs message="WARNING: [XFORM 203-561] Updating loop lower bound from 0 to 128 for loop 'Loop-0-0' in function 'hls::Array2D2Mat&lt;32, 128, unsigned char, 0>'." projectName="SIFT" solutionName="solution1" date="2018-12-05T18:25:55.862+0800" type="Warning"/>
        <logs message="WARNING: [XFORM 203-1103] Ignored data pack directive on non-struct variable '_src1.data_stream.V' (image_core.cpp:28)." projectName="SIFT" solutionName="solution1" date="2018-12-05T18:24:46.763+0800" type="Warning"/>
        <logs message="WARNING: [XFORM 203-1103] Ignored data pack directive on non-struct variable '_src0.data_stream.V' (image_core.cpp:27)." projectName="SIFT" solutionName="solution1" date="2018-12-05T18:24:45.150+0800" type="Warning"/>
        <logs message="WARNING: [XFORM 203-1103] Ignored data pack directive on non-struct variable '_dst1.data_stream.V' (image_core.cpp:34)." projectName="SIFT" solutionName="solution1" date="2018-12-05T18:24:45.146+0800" type="Warning"/>
        <logs message="WARNING: [XFORM 203-1103] Ignored data pack directive on non-struct variable '_dst0.data_stream.V' (image_core.cpp:33)." projectName="SIFT" solutionName="solution1" date="2018-12-05T18:24:45.143+0800" type="Warning"/>
        <logs message="WARNING: [SYNCHK 200-120] ./sift.h:518: multiplication is assumed not to overflow by default, otherwise, please add option '-fwrapv'." projectName="SIFT" solutionName="solution1" date="2018-12-05T18:24:41.814+0800" type="Warning"/>
        <logs message="WARNING: [SYNCHK 200-23] r:/builds/2018.2/continuous/2018_06_14_2258646/src/products/hls/hls_lib/hlsmath/include\hls_sqrt_apfixed.h:264: variable-indexed range selection may cause suboptimal QoR." projectName="SIFT" solutionName="solution1" date="2018-12-05T18:24:41.804+0800" type="Warning"/>
      </synLog>
      <simLog/>
      <mgLog/>
      <packageLog>
        <logs message="WARNING: [IP_Flow 19-4832] The IP name 'SIFT2_Core_ap_uitofp_0_no_dsp_32' you have specified is long. The Windows operating system has path length limitations. It is recommended you use shorter names to reduce the likelihood of issues." projectName="SIFT" solutionName="solution1" date="2018-12-05T18:38:50.228+0800" type="Warning"/>
        <logs message="WARNING: [IP_Flow 19-4832] The IP name 'SIFT2_Core_ap_sitofp_0_no_dsp_32' you have specified is long. The Windows operating system has path length limitations. It is recommended you use shorter names to reduce the likelihood of issues." projectName="SIFT" solutionName="solution1" date="2018-12-05T18:38:48.954+0800" type="Warning"/>
        <logs message="WARNING: [IP_Flow 19-4832] The IP name 'SIFT2_Core_ap_fsub_2_full_dsp_32' you have specified is long. The Windows operating system has path length limitations. It is recommended you use shorter names to reduce the likelihood of issues." projectName="SIFT" solutionName="solution1" date="2018-12-05T18:38:47.716+0800" type="Warning"/>
        <logs message="WARNING: [IP_Flow 19-4832] The IP name 'SIFT2_Core_ap_fsqrt_5_no_dsp_32' you have specified is long. The Windows operating system has path length limitations. It is recommended you use shorter names to reduce the likelihood of issues." projectName="SIFT" solutionName="solution1" date="2018-12-05T18:38:46.455+0800" type="Warning"/>
        <logs message="WARNING: [IP_Flow 19-4832] The IP name 'SIFT2_Core_ap_fpext_0_no_dsp_32' you have specified is long. The Windows operating system has path length limitations. It is recommended you use shorter names to reduce the likelihood of issues." projectName="SIFT" solutionName="solution1" date="2018-12-05T18:38:45.309+0800" type="Warning"/>
        <logs message="WARNING: [IP_Flow 19-4832] The IP name 'SIFT2_Core_ap_fmul_0_max_dsp_32' you have specified is long. The Windows operating system has path length limitations. It is recommended you use shorter names to reduce the likelihood of issues." projectName="SIFT" solutionName="solution1" date="2018-12-05T18:38:44.170+0800" type="Warning"/>
        <logs message="WARNING: [IP_Flow 19-4832] The IP name 'SIFT2_Core_ap_flog_4_full_dsp_32' you have specified is long. The Windows operating system has path length limitations. It is recommended you use shorter names to reduce the likelihood of issues." projectName="SIFT" solutionName="solution1" date="2018-12-05T18:38:42.899+0800" type="Warning"/>
        <logs message="WARNING: [IP_Flow 19-4832] The IP name 'SIFT2_Core_ap_fexp_3_full_dsp_32' you have specified is long. The Windows operating system has path length limitations. It is recommended you use shorter names to reduce the likelihood of issues." projectName="SIFT" solutionName="solution1" date="2018-12-05T18:38:41.567+0800" type="Warning"/>
        <logs message="WARNING: [IP_Flow 19-4832] The IP name 'SIFT2_Core_ap_fdiv_5_no_dsp_32' you have specified is long. The Windows operating system has path length limitations. It is recommended you use shorter names to reduce the likelihood of issues." projectName="SIFT" solutionName="solution1" date="2018-12-05T18:38:40.243+0800" type="Warning"/>
        <logs message="WARNING: [IP_Flow 19-4832] The IP name 'SIFT2_Core_ap_fcmp_0_no_dsp_32' you have specified is long. The Windows operating system has path length limitations. It is recommended you use shorter names to reduce the likelihood of issues." projectName="SIFT" solutionName="solution1" date="2018-12-05T18:38:39.018+0800" type="Warning"/>
        <logs message="WARNING: [IP_Flow 19-4832] The IP name 'SIFT2_Core_ap_fadd_2_full_dsp_32' you have specified is long. The Windows operating system has path length limitations. It is recommended you use shorter names to reduce the likelihood of issues." projectName="SIFT" solutionName="solution1" date="2018-12-05T18:38:37.645+0800" type="Warning"/>
      </packageLog>
      <csimLog/>
    </logs>
  </warningLogs>
</vivadoHLSLog:LogRoot>
